wsjsonrpc/__init__.py
wsjsonrpc/_version.py
wsjsonrpc/exception.py
wsjsonrpc/factory.py
wsjsonrpc/protocol.py
wsjsonrpc-0.0.2.dist-info/LICENSE
wsjsonrpc-0.0.2.dist-info/METADATA
wsjsonrpc-0.0.2.dist-info/WHEEL
wsjsonrpc-0.0.2.dist-info/top_level.txt
wsjsonrpc-0.0.2.dist-info/RECORD
