Metadata-Version: 2.1
Name: wsjsonrpc
Version: 0.0.2
Summary: JSON-RPC 2.0 over websockets
Home-page: https://gitlab.com/donalm/wsjsonrpc
Author: Dónal McMullan
Author-email: donal.mcmullan@gmail.com
License: UNKNOWN
Keywords: websocket,twisted,autobahn,jsonrpc,rpc
Platform: UNKNOWN
Classifier: Topic :: Communications
Classifier: Topic :: System :: Distributed Computing
Classifier: License :: OSI Approved :: MIT License
Classifier: Framework :: Twisted
Classifier: Operating System :: OS Independent
Classifier: Intended Audience :: Developers
Classifier: Development Status :: 4 - Beta
Classifier: Programming Language :: Python
Classifier: Programming Language :: Python :: 2
Classifier: Programming Language :: Python :: 2.7
Classifier: Programming Language :: Python :: 3
Classifier: Programming Language :: Python :: 3.6
Classifier: Programming Language :: Python :: 3.7
Classifier: Programming Language :: Python :: Implementation :: CPython
Classifier: Programming Language :: Python :: Implementation :: PyPy
Requires-Python: >=2.7, !=3.0.*, !=3.1.*, !=3.2.*, !=3.3.*, !=3.4.*, !=3.5.*, <4
Requires-Dist: autobahn
Requires-Dist: twisted
